mando/__init__.py
mando/core.py
mando/rst_text_formatter.py
mando/utils.py
mando/napoleon/__init__.py
mando/napoleon/docstring.py
mando/napoleon/iterators.py
mando/napoleon/pycompat.py
mando/tests/__init__.py
mando/tests/capture.py
mando/tests/run.py
mando/tests/test_core.py
mando/tests/test_google.py
mando/tests/test_numpy.py
mando/tests/test_unicode_docstring_on_py2.py
mando/tests/test_utils.py
mando-0.8.1.dist-info/LICENSE
mando-0.8.1.dist-info/METADATA
mando-0.8.1.dist-info/WHEEL
mando-0.8.1.dist-info/top_level.txt
mando-0.8.1.dist-info/RECORD
