Metadata-Version: 2.1
Name: mando
Version: 0.8.1
Summary: Create Python CLI apps with little to no effort at all!
Home-page: https://mando.readthedocs.org/
Download-URL: https://pypi.python.org/mando/
Author: Michele Lacchia
Author-email: michelelacchia@gmail.com
License: MIT
Keywords: argparse,argument parser,arguments,cli,command line,commands,decorator,dispatch,flags,getopt,options,optparse,parser,subcommands
Platform: any
Classifier: Development Status :: 5 - Production/Stable
Classifier: Environment :: Console
Classifier: Intended Audience :: Developers
Classifier: License :: OSI Approved :: MIT License
Classifier: Natural Language :: English
Classifier: Operating System :: OS Independent
Classifier: Programming Language :: Python
Classifier: Programming Language :: Python :: 3
Classifier: Programming Language :: Python :: 3.1
Classifier: Programming Language :: Python :: 3.2
Classifier: Programming Language :: Python :: 3.3
Classifier: Programming Language :: Python :: 3.4
Classifier: Programming Language :: Python :: 3.5
Classifier: Programming Language :: Python :: 3.6
Classifier: Programming Language :: Python :: 3.7
Classifier: Programming Language :: Python :: 3.8
Classifier: Programming Language :: Python :: Implementation :: CPython
Classifier: Programming Language :: Python :: Implementation :: PyPy
Classifier: Topic :: Software Development
Classifier: Topic :: Software Development :: Libraries :: Python Modules
Classifier: Topic :: Utilities
License-File: LICENSE
Provides-Extra: restructuredtext
Requires-Dist: rst2ansi; extra == "restructuredtext"
